redis_gadgets/__init__.py
redis_gadgets/unique_count.py
redis_gadgets-0.1.7.dist-info/DESCRIPTION.rst
redis_gadgets-0.1.7.dist-info/METADATA
redis_gadgets-0.1.7.dist-info/metadata.json
redis_gadgets-0.1.7.dist-info/pbr.json
redis_gadgets-0.1.7.dist-info/RECORD
redis_gadgets-0.1.7.dist-info/top_level.txt
redis_gadgets-0.1.7.dist-info/WHEEL
