Metadata-Version: 2.0
Name: redis-gadgets
Version: 0.1.7
Summary: Light-weight tools to implement high-level features in Redis
Home-page: http://keep.com
Author: Keep.com development team
Author-email: opensource@keep.com
License: MIT
Platform: UNKNOWN
Requires-Dist: nose (>=1.3.0)
Requires-Dist: redis (>=2.0.0)
